LICENSE
MANIFEST.in
README.md
setup.cfg
setup.py
psat_server_web/.DS_Store
psat_server_web/__init__.py
psat_server_web/__version__.py
psat_server_web.egg-info/PKG-INFO
psat_server_web.egg-info/SOURCES.txt
psat_server_web.egg-info/dependency_links.txt
psat_server_web.egg-info/not-zip-safe
psat_server_web.egg-info/requires.txt
psat_server_web.egg-info/top_level.txt
psat_server_web/atlas/.DS_Store
psat_server_web/atlas/__init__.py
psat_server_web/atlas/cow_backup.txt
psat_server_web/atlas/django-default.log
psat_server_web/atlas/generate_mod_wsgi_apachectl.sh
psat_server_web/atlas/generate_mod_wsgi_apachectl_test.sh
psat_server_web/atlas/manage.py
psat_server_web/atlas/tcs_detection_lists.sql
psat_server_web/atlas/test.py
psat_server_web/atlas/accounts/admin.py
psat_server_web/atlas/accounts/apps.py
psat_server_web/atlas/accounts/forms.py
psat_server_web/atlas/accounts/models.py
psat_server_web/atlas/accounts/permissions.py
psat_server_web/atlas/accounts/signals.py
psat_server_web/atlas/accounts/urls.py
psat_server_web/atlas/accounts/utils.py
psat_server_web/atlas/accounts/views.py
psat_server_web/atlas/accounts/migrations/0001_initial.py
psat_server_web/atlas/accounts/migrations/0002_groupprofile_api_write_access.py
psat_server_web/atlas/accounts/migrations/0003_globalpermissions.py
psat_server_web/atlas/accounts/migrations/0004_userprofile.py
psat_server_web/atlas/accounts/migrations/0005_userprofile_image_userprofile_image_b64.py
psat_server_web/atlas/accounts/migrations/0006_alter_userprofile_image.py
psat_server_web/atlas/accounts/migrations/__init__.py
psat_server_web/atlas/atlas/__init__.py
psat_server_web/atlas/atlas/apiutils.py
psat_server_web/atlas/atlas/commonqueries.py
psat_server_web/atlas/atlas/dbviews.py
psat_server_web/atlas/atlas/django-default.log
psat_server_web/atlas/atlas/document.sh
psat_server_web/atlas/atlas/formchoices.py
psat_server_web/atlas/atlas/helpers.py
psat_server_web/atlas/atlas/insert_gravity_event.sql
psat_server_web/atlas/atlas/lightcurvequeries.py
psat_server_web/atlas/atlas/models.py
psat_server_web/atlas/atlas/settings.py
psat_server_web/atlas/atlas/sqlpaginator.py
psat_server_web/atlas/atlas/urls.py
psat_server_web/atlas/atlas/view_celestial.py
